setup.py
wfcollection.py
wfposts.py
wfread.py
wfuri.py
wfuser.py
writefreely.py
writefreelyapi.egg-info/PKG-INFO
writefreelyapi.egg-info/SOURCES.txt
writefreelyapi.egg-info/dependency_links.txt
writefreelyapi.egg-info/requires.txt
writefreelyapi.egg-info/top_level.txt