Metadata-Version: 1.0
Name: writefreelyapi
Version: 0.6
Summary: An API client library for WriteFreely
Home-page: https://github.com/cjeller1592/Writeas-API
Author: CJ Eller
Author-email: cjeller1592@gmail.com
License: MIT
Platform: UNKNOWN
